lambda_local/__init__.py
lambda_local_python-0.0.4.dist-info/DESCRIPTION.rst
lambda_local_python-0.0.4.dist-info/METADATA
lambda_local_python-0.0.4.dist-info/RECORD
lambda_local_python-0.0.4.dist-info/WHEEL
lambda_local_python-0.0.4.dist-info/entry_points.txt
lambda_local_python-0.0.4.dist-info/metadata.json
lambda_local_python-0.0.4.dist-info/top_level.txt
