Metadata-Version: 2.0
Name: lambda-local-python
Version: 0.0.4
Summary: Run/debug python aws lambda functions locally
Home-page: https://github.com/willwhy/lambda-local-python
Author: Will Wenhua Yang
Author-email: will.whyang@gmail.com
License: MIT
Keywords: AWS Lambda,vscode,Visual Studio Code,code
Platform: UNKNOWN
Classifier: Development Status :: 3 - Alpha
Classifier: Operating System :: POSIX
Classifier: Programming Language :: Python
Classifier: Programming Language :: Python :: 2.7
Classifier: Programming Language :: Python :: 3.6
Classifier: License :: OSI Approved :: MIT License
